quantum_flows/__init__.py
quantum_flows/quantum_flows.py
quantum_flows/quantum_flows.py.bck
quantum_flows-0.1.20.dist-info/LICENSE
quantum_flows-0.1.20.dist-info/METADATA
quantum_flows-0.1.20.dist-info/WHEEL
quantum_flows-0.1.20.dist-info/RECORD
