Metadata-Version: 2.3
Name: quantum-flows
Version: 0.1.20
Summary: A python library for interacting with Transilvania-Quantum Quantum Flows quantum computing API backbone.
License: MIT
Author: Radu Marginean
Author-email: radu.marginean@transilvania-quantum.com
Requires-Python: >=3.10,<4.0
Classifier: License :: OSI Approved :: MIT License
Classifier: Programming Language :: Python :: 3
Classifier: Programming Language :: Python :: 3.10
Classifier: Programming Language :: Python :: 3.11
Classifier: Programming Language :: Python :: 3.12
Classifier: Programming Language :: Python :: 3.13
Requires-Dist: cryptography (>=44.0.2,<45.0.0)
Requires-Dist: python-keycloak (>=4.7.3,<5.0.0)
Requires-Dist: qiskit (==1.4.4)
Requires-Dist: qiskit-nature (>=0.7.2,<0.8.0)
Requires-Dist: qiskit-optimization (==0.7.0)
Project-URL: Repository, https://github.com/Transilvania-Quantum/quantum-flows
